./.env.example
./LICENSE
./PKG-INFO
./README.md
./README_zh.md
./client.py
./language.json
./package_name
./pyproject.toml
./requirements.txt
./server.py
./tool_test.py
iflow_mcp_lrriver_zotero_mcp-0.1.0.dist-info/METADATA
iflow_mcp_lrriver_zotero_mcp-0.1.0.dist-info/WHEEL
iflow_mcp_lrriver_zotero_mcp-0.1.0.dist-info/entry_points.txt
iflow_mcp_lrriver_zotero_mcp-0.1.0.dist-info/licenses/LICENSE
iflow_mcp_lrriver_zotero_mcp-0.1.0.dist-info/RECORD
