Metadata-Version: 2.4
Name: iflow-mcp_lrriver-zotero_mcp
Version: 0.1.0
Summary: A Model Context Protocol (MCP) server for interacting with Zotero libraries
License-File: LICENSE
Requires-Python: >=3.11
Requires-Dist: fastmcp>=2.8.1
Requires-Dist: python-dotenv>=1.1.0
Requires-Dist: pyzotero>=1.6.11
